endpoint_pulse/__init__.py
endpoint_pulse/app.py
endpoint_pulse/endpoint_pulse_runner.py
endpoint_pulse/static/css/modern.css
endpoint_pulse/static/css/style.css
endpoint_pulse/static/js/app.js
endpoint_pulse/templates/index.html
endpoint_pulse-0.2.3.dist-info/licenses/LICENSE
endpoint_pulse-0.2.3.dist-info/METADATA
endpoint_pulse-0.2.3.dist-info/WHEEL
endpoint_pulse-0.2.3.dist-info/entry_points.txt
endpoint_pulse-0.2.3.dist-info/top_level.txt
endpoint_pulse-0.2.3.dist-info/RECORD
