Metadata-Version: 2.4
Name: endpoint-pulse
Version: 0.2.3
Summary: Endpoint Pulse - a small FastAPI + Jinja app to organize and probe URLs
Author: Andreas Jung <info@zopyx.com>
License: WTFPL
Project-URL: Homepage, https://github.com/zopyx/zopyx-url-checker-dashboard
Classifier: License :: OSI Approved :: The Unlicense (Unlicense)
Requires-Python: >=3.9
License-File: LICENSE
Requires-Dist: fastapi<1.0,>=0.111
Requires-Dist: uvicorn[standard]>=0.30
Requires-Dist: jinja2>=3.1
Requires-Dist: httpx>=0.27
Requires-Dist: pydantic>=2.8
Requires-Dist: requests>=2.32
Requires-Dist: python-multipart
Dynamic: license-file
